pytest_streaming/__init__.py
pytest_streaming/config.py
pytest_streaming/plugin.py
pytest_streaming/abstracts/__init__.py
pytest_streaming/abstracts/markers.py
pytest_streaming/pubsub/__init__.py
pytest_streaming/pubsub/markers.py
pytest_streaming/pubsub/plugin.py
pytest_streaming/pubsub/publisher.py
pytest_streaming/pulsar/__init__.py
pytest_streaming/pulsar/client.py
pytest_streaming/pulsar/markers.py
pytest_streaming/pulsar/plugin.py
pytest_streaming-1.4.0.dist-info/METADATA
pytest_streaming-1.4.0.dist-info/WHEEL
pytest_streaming-1.4.0.dist-info/entry_points.txt
pytest_streaming-1.4.0.dist-info/licenses/LICENSE
pytest_streaming-1.4.0.dist-info/RECORD
