Metadata-Version: 2.4
Name: pytest-streaming
Version: 1.4.0
Summary: Plugin for testing pubsub, pulsar, and kafka systems with pytest locally and in ci/cd
Project-URL: Repository, https://github.com/nachatz/pytest-streaming
Author-email: Nikolas Achatz <nil@gmail.com>
Maintainer-email: Nikolas Achatz <nil@gmail.com>
License:                                  Apache License
License-File: LICENSE
Classifier: Framework :: Pytest
Classifier: Programming Language :: Python :: 3.10
Classifier: Programming Language :: Python :: 3.11
Classifier: Programming Language :: Python :: 3.12
Classifier: Programming Language :: Python :: 3.13
Requires-Python: >=3.10
Requires-Dist: google-cloud-pubsub>=2.29.0
Requires-Dist: httpx>=0.28.1
Requires-Dist: pulsar-client>=3.5.0
Requires-Dist: pytest>=8.3.5
Requires-Dist: types-protobuf>=5.29.1.20250315
